zmodels/__init__.py
zmodels/core.py
zmodels/exceptions.py
zmodels-0.1.5.dist-info/AUTHORS.rst
zmodels-0.1.5.dist-info/LICENSE
zmodels-0.1.5.dist-info/METADATA
zmodels-0.1.5.dist-info/WHEEL
zmodels-0.1.5.dist-info/top_level.txt
zmodels-0.1.5.dist-info/RECORD
