Metadata-Version: 2.1
Name: zmodels
Version: 0.1.5
Summary: Basic implementation of the repository pattern for database access.
Home-page: https://github.com/tchappui/ZModels
Author: Thierry Chappuis
Author-email: thierry@chappuis.io
License: MIT license
Keywords: zmodels
Platform: UNKNOWN
Classifier: Development Status :: 2 - Pre-Alpha
Classifier: Intended Audience :: Developers
Classifier: License :: OSI Approved :: MIT License
Classifier: Natural Language :: English
Classifier: Programming Language :: Python :: 3.6
Classifier: Programming Language :: Python :: 3.7
Requires-Dist: records
